pytest_clerk/__init__.py
pytest_clerk/clerk.py
pytest_clerk-4.1.2.dist-info/METADATA
pytest_clerk-4.1.2.dist-info/WHEEL
pytest_clerk-4.1.2.dist-info/entry_points.txt
pytest_clerk-4.1.2.dist-info/licenses/LICENSE
pytest_clerk-4.1.2.dist-info/RECORD
