Metadata-Version: 2.4
Name: pytest-clerk
Version: 4.1.2
Summary: A set of pytest fixtures to help with integration testing with Clerk.
License-Expression: MIT
License-File: LICENSE
Author: Ryan Causey
Author-email: ryan.causey@munipal.io
Requires-Python: >=3.10,<4.0
Classifier: Framework :: Pytest
Provides-Extra: aws
Requires-Dist: httpx (>=0.28.0,<1.0.0)
Requires-Dist: limits (>=4.0.1,<5.7.0)
Requires-Dist: pytest (>=8.0.0,<10.0.0)
Requires-Dist: pytest-aws-fixtures (>=3.0.0,<4.0) ; extra == "aws"
Requires-Dist: python-decouple (>=3.0,<4.0)
Requires-Dist: tenacity (>=9.0.0,<10.0.0)
